hdfs_analyze/__init__.py
hdfs_analyze/config_docling.py
hdfs_analyze/config_hdfs.py
hdfs_analyze/connect_hdfs.py
hdfs_analyze/connect_mongo.py
hdfs_analyze/extract_content_no_docling_v2.py
hdfs_analyze/forward_config.py
hdfs_analyze/pipe_line_obsei.py
hdfs_analyze/post_install.py
hdfs_analyze/obsei_module/__init__.py
hdfs_analyze/obsei_module/obsei/__init__.py
hdfs_analyze/obsei_module/obsei/_version.py
hdfs_analyze/obsei_module/obsei/configuration.py
hdfs_analyze/obsei_module/obsei/payload.py
hdfs_analyze/obsei_module/obsei/process_workflow.py
hdfs_analyze/obsei_module/obsei/processor.py
hdfs_analyze/obsei_module/obsei/analyzer/__init__.py
hdfs_analyze/obsei_module/obsei/analyzer/base_analyzer.py
hdfs_analyze/obsei_module/obsei/analyzer/classification_analyzer.py
hdfs_analyze/obsei_module/obsei/analyzer/dummy_analyzer.py
hdfs_analyze/obsei_module/obsei/analyzer/ner_analyzer.py
hdfs_analyze/obsei_module/obsei/analyzer/pii_analyzer.py
hdfs_analyze/obsei_module/obsei/analyzer/sentiment_analyzer.py
hdfs_analyze/obsei_module/obsei/analyzer/test_ner.py
hdfs_analyze/obsei_module/obsei/analyzer/translation_analyzer.py
hdfs_analyze/obsei_module/obsei/misc/__init__.py
hdfs_analyze/obsei_module/obsei/misc/gpu_util.py
hdfs_analyze/obsei_module/obsei/misc/utils.py
hdfs_analyze/obsei_module/obsei/misc/web_search.py
hdfs_analyze/obsei_module/obsei/misc/youtube_reviews_scrapper.py
hdfs_analyze/obsei_module/obsei/postprocessor/__init__.py
hdfs_analyze/obsei_module/obsei/postprocessor/base_postprocessor.py
hdfs_analyze/obsei_module/obsei/postprocessor/inference_aggregator.py
hdfs_analyze/obsei_module/obsei/postprocessor/inference_aggregator_function.py
hdfs_analyze/obsei_module/obsei/postprocessor/test3.py
hdfs_analyze/obsei_module/obsei/preprocessor/__init__.py
hdfs_analyze/obsei_module/obsei/preprocessor/base_preprocessor.py
hdfs_analyze/obsei_module/obsei/preprocessor/text_cleaner.py
hdfs_analyze/obsei_module/obsei/preprocessor/text_cleaning_function.py
hdfs_docling_analyze-0.4.0.dist-info/METADATA
hdfs_docling_analyze-0.4.0.dist-info/WHEEL
hdfs_docling_analyze-0.4.0.dist-info/top_level.txt
hdfs_docling_analyze-0.4.0.dist-info/RECORD
